default_deepcopy/__init__.py
default_deepcopy-0.0.1.dist-info/METADATA
default_deepcopy-0.0.1.dist-info/WHEEL
default_deepcopy-0.0.1.dist-info/licenses/LICENSE
default_deepcopy-0.0.1.dist-info/RECORD
