Metadata-Version: 2.4
Name: default_deepcopy
Version: 0.0.1
Summary: deepcopy, but if exception, return default value instead of raising exception
Project-URL: Homepage, https://github.com/zlliu246/default_deepcopy
Project-URL: Issues, https://github.com/zlliu246/default_deepcopy/issues
Author-email: Liu Zuo Lin <zlliu246@gmail.com>
License-File: LICENSE
Classifier: License :: OSI Approved :: MIT License
Classifier: Operating System :: OS Independent
Classifier: Programming Language :: Python :: 3
Requires-Python: >=3.8
